pass_cli/__init__.py
pass_cli/cli.py
pass_cli/database.py
pass_cli/utils.py
pass_cli/commands/__init__.py
pass_cli/commands/auth.py
pass_cli/commands/auth_check.py
pass_cli/commands/delete.py
pass_cli/commands/generate.py
pass_cli/commands/init.py
pass_cli/commands/list.py
pass_cli/commands/retrieve.py
pass_cli/commands/store.py
password_cli-0.1.6.dist-info/LICENSE
password_cli-0.1.6.dist-info/METADATA
password_cli-0.1.6.dist-info/WHEEL
password_cli-0.1.6.dist-info/entry_points.txt
password_cli-0.1.6.dist-info/top_level.txt
password_cli-0.1.6.dist-info/RECORD
