Metadata-Version: 2.2
Name: password-cli
Version: 0.1.6
Summary: A secure command-line password manager with sudo authentication
Home-page: https://github.com/umuttopalak/pass-cli
Author: Umut Topalak
Author-email: umuttopalak@hotmail.com
Project-URL: Bug Tracker, https://github.com/umuttopalak/pass-cli/issues
Project-URL: Documentation, https://github.com/umuttopalak/pass-cli#readme
Project-URL: Source Code, https://github.com/umuttopalak/pass-cli
Keywords: password-manager,security,cryptography,cli,command-line,sudo
Classifier: Development Status :: 4 - Beta
Classifier: Environment :: Console
Classifier: Intended Audience :: End Users/Desktop
Classifier: License :: OSI Approved :: MIT License
Classifier: Operating System :: OS Independent
Classifier: Programming Language :: Python :: 3
Classifier: Programming Language :: Python :: 3.8
Classifier: Programming Language :: Python :: 3.9
Classifier: Programming Language :: Python :: 3.10
Classifier: Programming Language :: Python :: 3.11
Classifier: Programming Language :: Python :: 3.12
Classifier: Topic :: Security
Classifier: Topic :: Security :: Cryptography
Classifier: Topic :: Utilities
Requires-Python: >=3.8
License-File: LICENSE
Requires-Dist: click>=8.0.0
Requires-Dist: cryptography>=3.4.7
Requires-Dist: keyring>=24.0.0
Requires-Dist: pyperclip>=1.8.2
Provides-Extra: dev
Requires-Dist: pytest>=7.0.0; extra == "dev"
Requires-Dist: pytest-cov>=4.0.0; extra == "dev"
Requires-Dist: pytest-mock>=3.10.0; extra == "dev"
Requires-Dist: black>=23.0.0; extra == "dev"
Requires-Dist: isort>=5.10.0; extra == "dev"
Requires-Dist: flake8>=4.0.0; extra == "dev"
Requires-Dist: mypy>=1.0.0; extra == "dev"
Dynamic: author
Dynamic: author-email
Dynamic: classifier
Dynamic: description
Dynamic: description-content-type
Dynamic: home-page
Dynamic: keywords
Dynamic: project-url
Dynamic: provides-extra
Dynamic: requires-dist
Dynamic: requires-python
Dynamic: summary
